{
	"$schema": "http://schema.management.azure.com/schemas/2015-01-01/deploymentTemplate.json#",
	"contentVersion": "1.0.0.0",
	"parameters": {
		"factoryName": {
			"type": "string",
			"metadata": "Data Factory name",
			"defaultValue": "codesave"
		},
		"LS_BlobStorage_connectionString": {
			"type": "secureString",
			"metadata": "Secure string for 'connectionString' of 'LS_BlobStorage'"
		},
		"LS_Sqlserver_password": {
			"type": "secureString",
			"metadata": "Secure string for 'password' of 'LS_Sqlserver'"
		},
		"LS_Sqlserver_properties_typeProperties_server": {
			"type": "string",
			"defaultValue": "trainingsqlservercodesavy.database.windows.net"
		},
		"LS_Sqlserver_properties_typeProperties_database": {
			"type": "string",
			"defaultValue": "SQLADFTraining"
		},
		"LS_Sqlserver_properties_typeProperties_userName": {
			"type": "string",
			"defaultValue": "gpavanku"
		}
	},
	"variables": {
		"factoryId": "[concat('Microsoft.DataFactory/factories/', parameters('factoryName'))]"
	},
	"resources": [
		{
			"name": "[concat(parameters('factoryName'), '/PL_COPY_ADLS_SQL_SERVER')]",
			"type": "Microsoft.DataFactory/factories/pipelines",
			"apiVersion": "2018-06-01",
			"properties": {
				"activities": [
					{
						"name": "Copy ADLS TO SQL",
						"description": "Moving data from ADLS TO SQL server",
						"type": "Copy",
						"dependsOn": [],
						"policy": {
							"timeout": "0.12:00:00",
							"retry": 0,
							"retryIntervalInSeconds": 30,
							"secureOutput": false,
							"secureInput": false
						},
						"userProperties": [
							{
								"name": "Source",
								"value": "inputfolder//Employee_Data.csv"
							},
							{
								"name": "Destination",
								"value": "HRP.Employee_Data"
							}
						],
						"typeProperties": {
							"source": {
								"type": "DelimitedTextSource",
								"additionalColumns": [
									{
										"name": "StartTime",
										"value": {
											"value": "@utcNow()",
											"type": "Expression"
										}
									}
								],
								"storeSettings": {
									"type": "AzureBlobStorageReadSettings",
									"recursive": true,
									"enablePartitionDiscovery": false
								},
								"formatSettings": {
									"type": "DelimitedTextReadSettings"
								}
							},
							"sink": {
								"type": "SqlServerSink",
								"writeBatchSize": 10,
								"writeBehavior": "insert",
								"sqlWriterUseTableLock": false,
								"tableOption": "autoCreate"
							},
							"enableStaging": false,
							"enableSkipIncompatibleRow": false,
							"translator": {
								"type": "TabularTranslator",
								"typeConversion": true,
								"typeConversionSettings": {
									"allowDataTruncation": true,
									"treatBooleanAsNumber": false
								}
							}
						},
						"inputs": [
							{
								"referenceName": "DS_ADLS_Employee",
								"type": "DatasetReference",
								"parameters": {}
							}
						],
						"outputs": [
							{
								"referenceName": "DS_SQL_Source_Table",
								"type": "DatasetReference",
								"parameters": {}
							}
						]
					}
				],
				"policy": {
					"elapsedTimeMetric": {}
				},
				"annotations": []
			},
			"dependsOn": [
				"[concat(variables('factoryId'), '/datasets/DS_ADLS_Employee')]",
				"[concat(variables('factoryId'), '/datasets/DS_SQL_Source_Table')]"
			]
		},
		{
			"name": "[concat(parameters('factoryName'), '/DS_ADLS_Employee')]",
			"type": "Microsoft.DataFactory/factories/datasets",
			"apiVersion": "2018-06-01",
			"properties": {
				"linkedServiceName": {
					"referenceName": "LS_BlobStorage",
					"type": "LinkedServiceReference"
				},
				"annotations": [],
				"type": "DelimitedText",
				"typeProperties": {
					"location": {
						"type": "AzureBlobStorageLocation",
						"fileName": "Employee_Data.csv",
						"container": "inputfolder"
					},
					"columnDelimiter": ",",
					"escapeChar": "\\",
					"firstRowAsHeader": true,
					"quoteChar": "\""
				},
				"schema": [
					{
						"name": "EMPLOYEE_ID",
						"type": "String"
					},
					{
						"name": "FIRST_NAME",
						"type": "String"
					},
					{
						"name": "LAST_NAME",
						"type": "String"
					},
					{
						"name": "EMAIL",
						"type": "String"
					},
					{
						"name": "PHONE_NUMBER",
						"type": "String"
					},
					{
						"name": "HIRE_DATE",
						"type": "String"
					},
					{
						"name": "JOB_ID",
						"type": "String"
					},
					{
						"name": "SALARY",
						"type": "String"
					},
					{
						"name": "COMMISSION_PCT",
						"type": "String"
					},
					{
						"name": "MANAGER_ID",
						"type": "String"
					},
					{
						"name": "DEPARTMENT_ID",
						"type": "String"
					}
				]
			},
			"dependsOn": [
				"[concat(variables('factoryId'), '/linkedServices/LS_BlobStorage')]"
			]
		},
		{
			"name": "[concat(parameters('factoryName'), '/DS_SQL_Source_Table')]",
			"type": "Microsoft.DataFactory/factories/datasets",
			"apiVersion": "2018-06-01",
			"properties": {
				"linkedServiceName": {
					"referenceName": "LS_Sqlserver",
					"type": "LinkedServiceReference"
				},
				"annotations": [],
				"type": "SqlServerTable",
				"schema": [
					{
						"name": "Empid",
						"type": "int",
						"precision": 10
					},
					{
						"name": "Empname",
						"type": "varchar"
					},
					{
						"name": "Empsalary",
						"type": "money",
						"precision": 19,
						"scale": 4
					},
					{
						"name": "Empdob",
						"type": "date"
					}
				],
				"typeProperties": {
					"schema": "HRP",
					"table": "Employee_Data"
				}
			},
			"dependsOn": [
				"[concat(variables('factoryId'), '/linkedServices/LS_Sqlserver')]"
			]
		},
		{
			"name": "[concat(parameters('factoryName'), '/LS_BlobStorage')]",
			"type": "Microsoft.DataFactory/factories/linkedServices",
			"apiVersion": "2018-06-01",
			"properties": {
				"annotations": [],
				"type": "AzureBlobStorage",
				"typeProperties": {
					"connectionString": "[parameters('LS_BlobStorage_connectionString')]"
				},
				"connectVia": {
					"referenceName": "Azure-IR",
					"type": "IntegrationRuntimeReference"
				}
			},
			"dependsOn": [
				"[concat(variables('factoryId'), '/integrationRuntimes/Azure-IR')]"
			]
		},
		{
			"name": "[concat(parameters('factoryName'), '/LS_Sqlserver')]",
			"type": "Microsoft.DataFactory/factories/linkedServices",
			"apiVersion": "2018-06-01",
			"properties": {
				"annotations": [],
				"type": "SqlServer",
				"typeProperties": {
					"server": "[parameters('LS_Sqlserver_properties_typeProperties_server')]",
					"database": "[parameters('LS_Sqlserver_properties_typeProperties_database')]",
					"encrypt": "mandatory",
					"trustServerCertificate": false,
					"authenticationType": "SQL",
					"userName": "[parameters('LS_Sqlserver_properties_typeProperties_userName')]",
					"password": {
						"type": "SecureString",
						"value": "[parameters('LS_Sqlserver_password')]"
					}
				},
				"connectVia": {
					"referenceName": "Azure-IR",
					"type": "IntegrationRuntimeReference"
				}
			},
			"dependsOn": [
				"[concat(variables('factoryId'), '/integrationRuntimes/Azure-IR')]"
			]
		},
		{
			"name": "[concat(parameters('factoryName'), '/AutoResolveIntegrationRuntime')]",
			"type": "Microsoft.DataFactory/factories/integrationRuntimes",
			"apiVersion": "2018-06-01",
			"properties": {
				"type": "Managed",
				"typeProperties": {
					"computeProperties": {
						"location": "AutoResolve",
						"dataFlowProperties": {
							"computeType": "General",
							"coreCount": 8,
							"timeToLive": 0
						}
					}
				},
				"managedVirtualNetwork": {
					"type": "ManagedVirtualNetworkReference",
					"referenceName": "default"
				}
			},
			"dependsOn": [
				"[concat(variables('factoryId'), '/managedVirtualNetworks/default')]"
			]
		},
		{
			"name": "[concat(parameters('factoryName'), '/Azure-IR')]",
			"type": "Microsoft.DataFactory/factories/integrationRuntimes",
			"apiVersion": "2018-06-01",
			"properties": {
				"type": "Managed",
				"typeProperties": {
					"computeProperties": {
						"location": "AutoResolve",
						"dataFlowProperties": {
							"computeType": "General",
							"coreCount": 32,
							"timeToLive": 10,
							"cleanup": false,
							"customProperties": []
						}
					}
				}
			},
			"dependsOn": []
		},
		{
			"name": "[concat(parameters('factoryName'), '/default')]",
			"type": "Microsoft.DataFactory/factories/managedVirtualNetworks",
			"apiVersion": "2018-06-01",
			"properties": {},
			"dependsOn": []
		}
	]
}